README.rst
setup.cfg
setup.py
pygql/__init__.py
pygql/client.py
pygql/dsl.py
pygql/gql.py
pygql/utils.py
pygql.egg-info/PKG-INFO
pygql.egg-info/SOURCES.txt
pygql.egg-info/dependency_links.txt
pygql.egg-info/requires.txt
pygql.egg-info/top_level.txt
pygql/transport/__init__.py
pygql/transport/batch_transport.py
pygql/transport/http.py
pygql/transport/local_schema.py
pygql/transport/requests.py
pygql/transport/session_transport.py