Metadata-Version: 1.1
Name: pygql
Version: 0.1.3
Summary: GraphQL client for Python
Home-page: https://github.com/itolosa/pygql
Author: Ignacio Tolosa
Author-email: ignacio@perejil.cl
License: MIT
Keywords: api graphql protocol rest relay gql client
Platform: UNKNOWN
Classifier: Development Status :: 3 - Alpha
Classifier: Intended Audience :: Developers
Classifier: Topic :: Software Development :: Libraries
Classifier: Programming Language :: Python :: 2
Classifier: Programming Language :: Python :: 2.7
Classifier: Programming Language :: Python :: 3
Classifier: Programming Language :: Python :: 3.3
Classifier: Programming Language :: Python :: 3.4
Classifier: Programming Language :: Python :: 3.5
Classifier: Programming Language :: Python :: Implementation :: PyPy
